devpackage.schema.json
devpm/__init__.py
devpm/__main__.py
devpm/_internal/__init__.py
devpm/_internal/cli/base_command.py
devpm/_internal/cli/main.py
devpm/_internal/commands/__init__.py
devpm/_internal/commands/base_run.py
devpm/_internal/commands/cr.py
devpm/_internal/commands/githook.py
devpm/_internal/commands/install.py
devpm/_internal/commands/lint.py
devpm/_internal/commands/pr.py
devpm/_internal/commands/restart.py
devpm/_internal/commands/run.py
devpm/_internal/commands/start.py
devpm/_internal/commands/stop.py
devpm/_internal/commands/test.py
devpm/_internal/commands/version.py
devpm/_internal/utils/__init__.py
devpm/_internal/utils/bash.py
devpm/_internal/utils/bin.py
devpm/_internal/utils/code.py
devpm/_internal/utils/context.py
devpm/_internal/utils/git.py
devpm/_internal/utils/log.py
devpm/_internal/utils/pip.py
example/version.py
devpm-1.2.0.dist-info/METADATA
devpm-1.2.0.dist-info/WHEEL
devpm-1.2.0.dist-info/entry_points.txt
devpm-1.2.0.dist-info/licenses/LICENSE
devpm-1.2.0.dist-info/RECORD
