Metadata-Version: 2.1
Name: devpm
Version: 1.2.0
Summary: Development package manager
Project-URL: Homepage, https://github.com/wequick/devpm
Project-URL: Bug Tracker, https://github.com/wequick/devpm/issues
Author-email: Galen Lin <oolgloo.2012@gmail.com>
License-File: LICENSE
Classifier: License :: OSI Approved :: MIT License
Classifier: Operating System :: OS Independent
Classifier: Programming Language :: Python :: 3
Requires-Python: >=3.7
